DenseNet/Layers.py
DenseNet/Models.py
DenseNet/Training.py
DenseNet/__init__.py
DenseNet_armhzjz-0.1.2.dist-info/LICENSE
DenseNet_armhzjz-0.1.2.dist-info/METADATA
DenseNet_armhzjz-0.1.2.dist-info/WHEEL
DenseNet_armhzjz-0.1.2.dist-info/top_level.txt
DenseNet_armhzjz-0.1.2.dist-info/RECORD
