Metadata-Version: 2.1
Name: DenseNet-armhzjz
Version: 0.1.2
Summary: A DenseNet implementation
Home-page: https://github.com/armhzjz/DenseNet
Author: Armando Hernandez
Author-email: armhzjz@pm.me
License: UNKNOWN
Platform: UNKNOWN
Classifier: Programming Language :: Python :: 3
Classifier: License :: OSI Approved :: MIT License
Classifier: Operating System :: OS Independent
Requires-Python: >=3.6
